{"lastUsed":1572255024396,"path":"C:\/git\/LightShaker\/AtollicWorkspace","projectCount":5,"recentFiles":[{"path":"\/Level\/src\/src","parentWorkspace":"C:\/git\/LightShaker\/AtollicWorkspace","name":"drvNvMemory.c","lastModified":1571667301680,"locationURI":"file:\/C:\/git\/LightShaker\/AtollicWorkspace\/shared\/src\/drvNvMemory.c"},{"path":"\/POV_Display\/src\/src","parentWorkspace":"C:\/git\/LightShaker\/AtollicWorkspace","name":"drvNvMemory.h","lastModified":1571749913122,"locationURI":"file:\/C:\/git\/LightShaker\/AtollicWorkspace\/shared\/src\/drvNvMemory.h"},{"path":"\/POV_Display\/src\/src","parentWorkspace":"C:\/git\/LightShaker\/AtollicWorkspace","name":"drvUSB.c","lastModified":1571670315157,"locationURI":"file:\/C:\/git\/LightShaker\/AtollicWorkspace\/shared\/src\/drvUSB.c"},{"path":"\/POV_Display\/src\/src","parentWorkspace":"C:\/git\/LightShaker\/AtollicWorkspace","name":"drvPower.c","lastModified":1571816098729,"locationURI":"file:\/C:\/git\/LightShaker\/AtollicWorkspace\/shared\/src\/drvPower.c"},{"path":"\/POV_Display\/src\/src","parentWorkspace":"C:\/git\/LightShaker\/AtollicWorkspace","name":"drvDisplay.c","lastModified":1571821974792,"locationURI":"file:\/C:\/git\/LightShaker\/AtollicWorkspace\/shared\/src\/drvDisplay.c"},{"path":"\/Level\/src\/src","parentWorkspace":"C:\/git\/LightShaker\/AtollicWorkspace","name":"drvApa102.c","lastModified":1571658293899,"locationURI":"file:\/C:\/git\/LightShaker\/AtollicWorkspace\/shared\/src\/drvApa102.c"},{"path":"\/Playground\/src","parentWorkspace":"C:\/git\/LightShaker\/AtollicWorkspace","name":"main.c","lastModified":1572255041200,"locationURI":"file:\/C:\/git\/LightShaker\/AtollicWorkspace\/Playground\/src\/main.c"},{"path":"\/Seismograph\/src","parentWorkspace":"C:\/git\/LightShaker\/AtollicWorkspace","name":"main.c","lastModified":1571144272087,"locationURI":"file:\/C:\/git\/LightShaker\/AtollicWorkspace\/Seismograph\/src\/main.c"},{"path":"\/POV_Display\/src","parentWorkspace":"C:\/git\/LightShaker\/AtollicWorkspace","name":"main.h","lastModified":1571664679059,"locationURI":"file:\/C:\/git\/LightShaker\/AtollicWorkspace\/POV_Display\/src\/main.h"},{"path":"\/POV_Display\/src\/src","parentWorkspace":"C:\/git\/LightShaker\/AtollicWorkspace","name":"drvApa102.h","lastModified":1571752088088,"locationURI":"file:\/C:\/git\/LightShaker\/AtollicWorkspace\/shared\/src\/drvApa102.h"},{"path":"\/Level\/src\/src","parentWorkspace":"C:\/git\/LightShaker\/AtollicWorkspace","name":"drvPower.c","lastModified":1571142974242,"locationURI":"file:\/C:\/git\/LightShaker\/AtollicWorkspace\/shared\/src\/drvPower.c"},{"path":"\/POV_Display\/src\/src","parentWorkspace":"C:\/git\/LightShaker\/AtollicWorkspace","name":"drvDisplay.h","lastModified":1571667811386,"locationURI":"file:\/C:\/git\/LightShaker\/AtollicWorkspace\/shared\/src\/drvDisplay.h"},{"path":"\/POV_Display\/src\/src","parentWorkspace":"C:\/git\/LightShaker\/AtollicWorkspace","name":"eeprom.c","lastModified":1571140239117,"locationURI":"file:\/C:\/git\/LightShaker\/AtollicWorkspace\/shared\/src\/eeprom.c"},{"path":"\/POV_Display\/src","parentWorkspace":"C:\/git\/LightShaker\/AtollicWorkspace","name":"stm32_it.c","lastModified":1571744724986,"locationURI":"file:\/C:\/git\/LightShaker\/AtollicWorkspace\/POV_Display\/src\/stm32_it.c"},{"path":"\/Playground\/src","parentWorkspace":"C:\/git\/LightShaker\/AtollicWorkspace","name":"main.h","lastModified":1571995296455,"locationURI":"file:\/C:\/git\/LightShaker\/AtollicWorkspace\/Playground\/src\/main.h"},{"path":"\/USB_Test\/src","parentWorkspace":"C:\/git\/LightShaker\/AtollicWorkspace","name":"stm32f0xx.h","lastModified":1571730534130,"locationURI":"file:\/C:\/git\/LightShaker\/AtollicWorkspace\/USB_Test\/src\/stm32f0xx.h"},{"path":"\/USB_Test\/src","parentWorkspace":"C:\/git\/LightShaker\/AtollicWorkspace","name":"main.c","lastModified":1571735244360,"locationURI":"file:\/C:\/git\/LightShaker\/AtollicWorkspace\/USB_Test\/src\/main.c"},{"path":"\/POV_Display","parentWorkspace":"C:\/git\/LightShaker\/AtollicWorkspace","name":"stm32_flash.ld","lastModified":1571744754776,"locationURI":"file:\/C:\/git\/LightShaker\/AtollicWorkspace\/POV_Display\/stm32_flash.ld"},{"path":"\/Level\/src\/src","parentWorkspace":"C:\/git\/LightShaker\/AtollicWorkspace","name":"drvNvMemory.h","lastModified":1571667554272,"locationURI":"file:\/C:\/git\/LightShaker\/AtollicWorkspace\/shared\/src\/drvNvMemory.h"},{"path":"\/USB_Test\/src","parentWorkspace":"C:\/git\/LightShaker\/AtollicWorkspace","name":"usb.c","lastModified":1571743130112,"locationURI":"file:\/C:\/git\/LightShaker\/AtollicWorkspace\/USB_Test\/src\/usb.c"},{"path":"\/POV_Display\/src","parentWorkspace":"C:\/git\/LightShaker\/AtollicWorkspace","name":"configConsole.c","lastModified":1571744935798,"locationURI":"file:\/C:\/git\/LightShaker\/AtollicWorkspace\/POV_Display\/src\/configConsole.c"},{"path":"\/POV_Display\/src\/src","parentWorkspace":"C:\/git\/LightShaker\/AtollicWorkspace","name":"drvNvMemory.c","lastModified":1571752260578,"locationURI":"file:\/C:\/git\/LightShaker\/AtollicWorkspace\/shared\/src\/drvNvMemory.c"},{"path":"\/Playground\/src\/src","parentWorkspace":"C:\/git\/LightShaker\/AtollicWorkspace","name":"drvMMA8653.c","lastModified":1570771512143,"locationURI":"file:\/C:\/git\/LightShaker\/AtollicWorkspace\/shared\/src\/drvMMA8653.c"},{"path":"\/POV_Display\/Libraries\/STM32_USB_Device_Library\/Core\/src","parentWorkspace":"C:\/git\/LightShaker\/AtollicWorkspace","name":"usbd_core.c","lastModified":1571743870396,"locationURI":"file:\/C:\/git\/LightShaker\/AtollicWorkspace\/shared\/Libraries\/STM32_USB_Device_Library\/Core\/src\/usbd_core.c"},{"path":"\/Level\/src","parentWorkspace":"C:\/git\/LightShaker\/AtollicWorkspace","name":"main.c","lastModified":1571820470025,"locationURI":"file:\/C:\/git\/LightShaker\/AtollicWorkspace\/Level\/src\/main.c"},{"path":"\/POV_Display\/src","parentWorkspace":"C:\/git\/LightShaker\/AtollicWorkspace","name":"main.c","lastModified":1571752240693,"locationURI":"file:\/C:\/git\/LightShaker\/AtollicWorkspace\/POV_Display\/src\/main.c"},{"path":"\/Seismograph\/src","parentWorkspace":"C:\/git\/LightShaker\/AtollicWorkspace","name":"main.h","lastModified":1571143526377,"locationURI":"file:\/C:\/git\/LightShaker\/AtollicWorkspace\/Seismograph\/src\/main.h"},{"path":"\/POV_Display\/src\/src","parentWorkspace":"C:\/git\/LightShaker\/AtollicWorkspace","name":"drvApa102.c","lastModified":1571752133069,"locationURI":"file:\/C:\/git\/LightShaker\/AtollicWorkspace\/shared\/src\/drvApa102.c"}]}